{
    "display": {
        "title": {
            "text": "INGENIEUR : rang 2",
            "color": "#F41378",
            "bold": true
        },
        "description": {
            "text": "gagner 5 parties avec un ingénieur",
            "color": "green",
            "bold": false
        },
        "icon": {
            "item": "minecraft:redstone"
        },
        "frame": "task",
        "show_toast": true,
        "announce_to_chat": true,
        "hidden": false
    },
    "criteria": {
        "scoreboard_trigger": {
            "trigger": "minecraft:impossible"
          }
    },
    "rewards": {
        "function": "minecraft:achievements/recompences/rang2"
      },
    "parent": "pitchout:maitrise/ingenieur/adv16"
}